{
  "build": {
    "content": [
      {
        "files": [
          "**/*.md","**/*.yml"
        ],
        "exclude": [
          "**/obj/**",
          "mim/**",
          "**/includes/**"
        ]
      }
    ],
    "resource": [
      {
        "files": [
          "**/*.png",
          "**/*.jpg",
          "breadcrumb.json"
        ],
        "exclude": [
          "**/obj/**",
          "mim/**",
          "**/includes/**"
        ]
      }
    ],
    "overwrite": [],
    "externalReference": [],
    "globalMetadata": {
        "breadcrumb_path": "/powershell/mim/breadcrumb.json",
        "ms.devlang": "",
        "brand": ""
      },
    "fileMetadata": {},
    "template": [],
    "dest": "mim"
  }
}
